{
  "nodes": [
    {
      "id": 0,
      "lat": -40.060855,
      "lon": -21.003074999999985
    },
    {
      "id": 1,
      "lat": -40.246178,
      "lon": 64.973145
    },
    {
      "id": 2,
      "lat": -41.388414,
      "lon": 62.918701
    },
    {
      "id": 3,
      "lat": -42.716287,
      "lon": 59.282227
    },
    {
      "id": 4,
      "lat": -44.59053,
      "lon": 63.413086
    },
    {
      "id": 5,
      "lat": -43.038241,
      "lon": 55.393066
    },
    {
      "id": 6,
      "lat": -10.748318000000001,
      "lon": -72.22412099999998
    },
    {
      "id": 7,
      "lat": -10.977929,
      "lon": -73.037109
    },
    {
      "id": 8,
      "lat": -10.597047000000002,
      "lon": -75.84960899999999
    },
    {
      "id": 9,
      "lat": -12.599717000000002,
      "lon": -75.34423799999999
    },
    {
      "id": 10,
      "lat": -44.794737,
      "lon": 49.460449
    },
    {
      "id": 11,
      "lat": -44.93107,
      "lon": 53.459473
    },
    {
      "id": 12,
      "lat": -45.982363,
      "lon": 58.688965
    },
    {
      "id": 13,
      "lat": -44.707531,
      "lon": 67.758974
    },
    {
      "id": 14,
      "lat": -46.764509,
      "lon": 69.609375
    },
    {
      "id": 15,
      "lat": -50.338645,
      "lon": 80.332031
    },
    {
      "id": 16,
      "lat": -50.401586,
      "lon": 83.803711
    },
    {
      "id": 17,
      "lat": -51.399025,
      "lon": 77.958984
    },
    {
      "id": 18,
      "lat": -46.650496,
      "lon": 48.603516
    },
    {
      "id": 19,
      "lat": -50.694387,
      "lon": 49.152832
    },
    {
      "id": 20,
      "lat": -50.636559,
      "lon": 48.339844
    },
    {
      "id": 21,
      "lat": -56.446266,
      "lon": 52.272949
    },
    {
      "id": 22,
      "lat": -55.851105,
      "lon": 52.558594
    },
    {
      "id": 23,
      "lat": -46.676581,
      "lon": 47.746582
    },
    {
      "id": 24,
      "lat": -44.572786,
      "lon": 48.669434
    },
    {
      "id": 25,
      "lat": -54.315642,
      "lon": 76.816406
    },
    {
      "id": 26,
      "lat": -44.241737,
      "lon": 59.985352
    },
    {
      "id": 27,
      "lat": -47.175133,
      "lon": 55.810547
    },
    {
      "id": 28,
      "lat": -48.879087,
      "lon": 55.239258
    },
    {
      "id": 29,
      "lat": -43.019796,
      "lon": 54.580078
    },
    {
      "id": 30,
      "lat": -10.229368000000001,
      "lon": -77.58544899999998
    },
    {
      "id": 31,
      "lat": -47.25683,
      "lon": -130.830688
    },
    {
      "id": 32,
      "lat": -45.274589,
      "lon": -122.957862
    },
    {
      "id": 33,
      "lat": -39.858686,
      "lon": -114.543457
    },
    {
      "id": 34,
      "lat": -34.519117,
      "lon": -112.565918
    },
    {
      "id": 35,
      "lat": -43.023322,
      "lon": -131.506348
    },
    {
      "id": 36,
      "lat": -26.078217,
      "lon": -117.949219
    },
    {
      "id": 37,
      "lat": -25.223396,
      "lon": -118.366699
    },
    {
      "id": 38,
      "lat": -18.879617,
      "lon": -118.32275399999999
    },
    {
      "id": 39,
      "lat": -25.470484,
      "lon": -128.71581999999995
    },
    {
      "id": 40,
      "lat": -19.808054,
      "lon": -125.679951
    },
    {
      "id": 41,
      "lat": -49.090247,
      "lon": 68.598633
    },
    {
      "id": 42,
      "lat": -48.661917,
      "lon": 64.401855
    },
    {
      "id": 43,
      "lat": -47.867432,
      "lon": 59.941406
    },
    {
      "id": 44,
      "lat": -53.61964,
      "lon": 66.445313
    },
    {
      "id": 45,
      "lat": -52.812636,
      "lon": 80.57373
    },
    {
      "id": 46,
      "lat": -25.203624,
      "lon": -138.88916
    },
    {
      "id": 47,
      "lat": -28.803684,
      "lon": -145.151367
    },
    {
      "id": 48,
      "lat": -33.298413,
      "lon": -148.227539
    },
    {
      "id": 49,
      "lat": -33.266278,
      "lon": -139.817505
    },
    {
      "id": 50,
      "lat": -24.36598,
      "lon": -145.84559
    },
    {
      "id": 51,
      "lat": -34.593566,
      "lon": -154.939898
    },
    {
      "id": 52,
      "lat": -11.525221,
      "lon": -127.437305
    },
    {
      "id": 53,
      "lat": -33.599943,
      "lon": -139.152832
    },
    {
      "id": 54,
      "lat": -25.972569,
      "lon": -128.875122
    },
    {
      "id": 55,
      "lat": -47.271662,
      "lon": -132.033691
    },
    {
      "id": 56,
      "lat": -37.581138,
      "lon": -110.041308
    },
    {
      "id": 57,
      "lat": -38.925756,
      "lon": 70.444336
    },
    {
      "id": 58,
      "lat": -0.829334,
      "lon": -105.809326
    },
    {
      "id": 59,
      "lat": -0.620418,
      "lon": -105.276489
    },
    {
      "id": 60,
      "lat": -21.560385,
      "lon": -109.92919899999998
    },
    {
      "id": 61,
      "lat": -15.115754,
      "lon": -103.888758
    },
    {
      "id": 62,
      "lat": 0.570682,
      "lon": -105.3479
    },
    {
      "id": 63,
      "lat": -14.827156,
      "lon": -85.429688
    },
    {
      "id": 64,
      "lat": -14.327369,
      "lon": -91.2854
    },
    {
      "id": 65,
      "lat": -13.550387,
      "lon": -92.828979
    },
    {
      "id": 66,
      "lat": -20.593899,
      "lon": -85.03418
    },
    {
      "id": 67,
      "lat": -14.997793,
      "lon": -100.431519
    },
    {
      "id": 68,
      "lat": -13.839985,
      "lon": -97.338867
    },
    {
      "id": 69,
      "lat": -24.507424999999998,
      "lon": -95.73486299999999
    },
    {
      "id": 70,
      "lat": -23.302229999999998,
      "lon": -90.32959
    },
    {
      "id": 71,
      "lat": -28.379817,
      "lon": -97.734375
    },
    {
      "id": 72,
      "lat": -21.41372,
      "lon": -100.634766
    },
    {
      "id": 73,
      "lat": 0.482573,
      "lon": -108.621434
    },
    {
      "id": 74,
      "lat": 0.851998,
      "lon": -107.138672
    },
    {
      "id": 75,
      "lat": 0.291095,
      "lon": -107.633057
    },
    {
      "id": 76,
      "lat": -0.164721,
      "lon": -108.138428
    },
    {
      "id": 77,
      "lat": -30.600502,
      "lon": -96.87744099999999
    },
    {
      "id": 78,
      "lat": 1.707887,
      "lon": -106.567383
    },
    {
      "id": 79,
      "lat": 1.241284,
      "lon": -105.858765
    },
    {
      "id": 80,
      "lat": -0.175377,
      "lon": -106.303711
    },
    {
      "id": 81,
      "lat": 0.713983,
      "lon": -106.237793
    },
    {
      "id": 82,
      "lat": -0.785173,
      "lon": -106.594849
    },
    {
      "id": 83,
      "lat": -45.575399,
      "lon": -116.938477
    },
    {
      "id": 84,
      "lat": -0.48873,
      "lon": -107.561646
    },
    {
      "id": 85,
      "lat": -0.005349,
      "lon": -107.017822
    },
    {
      "id": 86,
      "lat": -1.049105,
      "lon": -108.308716
    },
    {
      "id": 87,
      "lat": -14.779314,
      "lon": -119.040234
    },
    {
      "id": 88,
      "lat": -45.341785,
      "lon": -114.98290999999999
    },
    {
      "id": 89,
      "lat": -31.088896,
      "lon": -99.667969
    },
    {
      "id": 90,
      "lat": -30.918196,
      "lon": -96.020508
    },
    {
      "id": 91,
      "lat": -0.043395,
      "lon": -105.430298
    },
    {
      "id": 92,
      "lat": -12.381686,
      "lon": -77.88208
    },
    {
      "id": 93,
      "lat": -14.694457000000002,
      "lon": -83.29867399999999
    },
    {
      "id": 94,
      "lat": -10.877768,
      "lon": -77.980957
    },
    {
      "id": 95,
      "lat": -15.44195,
      "lon": -83.419189
    },
    {
      "id": 96,
      "lat": -13.767961,
      "lon": -85.731812
    },
    {
      "id": 97,
      "lat": -13.314275,
      "lon": -74.707031
    },
    {
      "id": 98,
      "lat": -18.041333,
      "lon": -97.283936
    },
    {
      "id": 99,
      "lat": -18.621686,
      "lon": -97.130127
    },
    {
      "id": 100,
      "lat": -18.455102,
      "lon": -87.363281
    },
    {
      "id": 101,
      "lat": -8.405997,
      "lon": -91.40625
    },
    {
      "id": 102,
      "lat": -8.058242,
      "lon": -93.317871
    },
    {
      "id": 103,
      "lat": -10.074992,
      "lon": -96.152344
    },
    {
      "id": 104,
      "lat": -11.352638,
      "lon": -86.68212899999999
    },
    {
      "id": 105,
      "lat": -8.932004000000001,
      "lon": -92.54882799999999
    },
    {
      "id": 106,
      "lat": -11.676307000000001,
      "lon": -101.99707
    },
    {
      "id": 107,
      "lat": -12.991733,
      "lon": -100.206299
    },
    {
      "id": 108,
      "lat": -6.778101000000001,
      "lon": -96.78955099999999
    },
    {
      "id": 109,
      "lat": -64.318981,
      "lon": 37.617188
    },
    {
      "id": 110,
      "lat": -70.505928,
      "lon": 19.555664
    },
    {
      "id": 111,
      "lat": -70.33069,
      "lon": -1.362305
    },
    {
      "id": 112,
      "lat": -67.807465,
      "lon": -7.426758
    },
    {
      "id": 113,
      "lat": -67.26396,
      "lon": -8.206787
    },
    {
      "id": 114,
      "lat": -13.371776,
      "lon": -83.78173799999999
    },
    {
      "id": 115,
      "lat": -4.8470520000000015,
      "lon": -99.294434
    },
    {
      "id": 116,
      "lat": -12.342343000000001,
      "lon": -85.51757799999999
    },
    {
      "id": 117,
      "lat": -8.602400000000001,
      "lon": -85.58349599999998
    },
    {
      "id": 118,
      "lat": -11.998713,
      "lon": -81.58447299999999
    },
    {
      "id": 119,
      "lat": -12.471062000000002,
      "lon": -83.80371099999999
    },
    {
      "id": 120,
      "lat": -48.567483,
      "lon": -14.432187
    },
    {
      "id": 121,
      "lat": -47.60238,
      "lon": -23.115234
    },
    {
      "id": 122,
      "lat": -46.856545,
      "lon": -35.419922
    },
    {
      "id": 123,
      "lat": -47.98268,
      "lon": -47.118976
    },
    {
      "id": 124,
      "lat": -54.600732,
      "lon": -14.852335999999985
    },
    {
      "id": 125,
      "lat": -58.596612,
      "lon": -9.707042999999986
    },
    {
      "id": 126,
      "lat": -61.808829,
      "lon": -5.670159999999987
    },
    {
      "id": 127,
      "lat": -66.49295,
      "lon": -7.811279
    },
    {
      "id": 128,
      "lat": -66.477669,
      "lon": -7.130127
    },
    {
      "id": 129,
      "lat": -65.65037,
      "lon": 11.752391
    },
    {
      "id": 130,
      "lat": -65.589797,
      "lon": 12.420044
    },
    {
      "id": 131,
      "lat": -4.426317,
      "lon": -67.719727
    },
    {
      "id": 132,
      "lat": -0.09555100000000083,
      "lon": -57.28271499999999
    },
    {
      "id": 133,
      "lat": 1.6027869999999993,
      "lon": -85.53955099999999
    },
    {
      "id": 134,
      "lat": -4.123131,
      "lon": -42.231445
    },
    {
      "id": 135,
      "lat": -6.349589,
      "lon": -16.962891
    },
    {
      "id": 136,
      "lat": -2.189493,
      "lon": -4.87793
    },
    {
      "id": 137,
      "lat": 0.3656149999999992,
      "lon": -4.064940999999987
    },
    {
      "id": 138,
      "lat": -7.415532000000001,
      "lon": -59.69964699999999
    },
    {
      "id": 139,
      "lat": -51.719417,
      "lon": -20.670795
    },
    {
      "id": 140,
      "lat": -45.650189,
      "lon": -1.8676759999999866
    },
    {
      "id": 141,
      "lat": -37.014475,
      "lon": 27.92005
    },
    {
      "id": 142,
      "lat": -37.41216,
      "lon": 28.421631
    },
    {
      "id": 143,
      "lat": -60.098829,
      "lon": 8.608343000000014
    },
    {
      "id": 144,
      "lat": -60.616221,
      "lon": 9.492188
    },
    {
      "id": 145,
      "lat": -69.403623,
      "lon": 2.086943
    },
    {
      "id": 146,
      "lat": -21.287076,
      "lon": -48.349124
    },
    {
      "id": 147,
      "lat": -24.203911,
      "lon": -16.980351
    },
    {
      "id": 148,
      "lat": -44.978266,
      "lon": -2.438965
    }
  ],
  "edges": [
    {
      "from": 0,
      "to": 0,
      "distance": 1082821.2,
      "road_type": "land",
      "road_name": "Black Hollows",
      "coords": "-40.060855, -21.003075, -41.427369, -22.104492, -42.58625, -20.632324, -43.261833, -20.368652, -43.961634, -21.84082, -44.434101, -22.5, -45.660135, -21.181641, -46.558643, -22.192383, -47.60238, -23.115234"
    },
    {
      "from": 1,
      "to": 2,
      "distance": 220653.9,
      "road_type": "land",
      "road_name": "",
      "coords": "-40.246178, 64.973145, -40.68441, 64.605103, -40.942036, 64.209595, -41.173871, 63.550415, -41.388414, 62.918701"
    },
    {
      "from": 2,
      "to": 3,
      "distance": 339437.4,
      "road_type": "land",
      "road_name": "",
      "coords": "-41.388414, 62.918701, -41.544749, 62.265015, -41.888993, 61.056519, -42.393791, 59.688721, -42.716287, 59.282227"
    },
    {
      "from": 4,
      "to": 2,
      "distance": 371221.1,
      "road_type": "land",
      "road_name": "",
      "coords": "-44.59053, 63.413086, -44.083979, 63.588867, -43.640616, 63.764648, -43.289947, 63.764648, -42.856801, 63.632813, -42.258262, 63.347168, -41.388414, 62.918701"
    },
    {
      "from": 3,
      "to": 5,
      "distance": 335294.0,
      "road_type": "land",
      "road_name": "",
      "coords": "-42.716287, 59.282227, -42.620444, 59.128418, -43.063262, 58.161621, -43.111377, 57.485962, -43.139427, 56.826782, -43.079305, 56.343384, -43.067273, 55.947876, -43.038241, 55.393066"
    },
    {
      "from": 6,
      "to": 7,
      "distance": 287210.5,
      "road_type": "land",
      "road_name": "",
      "coords": "-10.748318, -72.224121, -10.496904, -72.520752, -10.794615, -72.383423, -10.589602, -72.729492, -10.913243, -72.531738, -10.713705, -72.89978, -10.999488, -72.696533, -10.977929, -73.037109"
    },
    {
      "from": 7,
      "to": 8,
      "distance": 326389.3,
      "road_type": "land",
      "road_name": "",
      "coords": "-10.977929, -73.037109, -10.740677, -73.476563, -10.514036, -74.003906, -10.362848, -74.597168, -10.37905, -75.08606, -10.465859, -75.618896, -10.597047, -75.849609"
    },
    {
      "from": 8,
      "to": 9,
      "distance": 231167.7,
      "road_type": "land",
      "road_name": "",
      "coords": "-10.597047, -75.849609, -11.010678, -75.805664, -11.500694, -75.739746, -11.973337, -75.52002, -12.599717, -75.344238"
    },
    {
      "from": 10,
      "to": 11,
      "distance": 317573.5,
      "road_type": "land",
      "road_name": "",
      "coords": "-44.794737, 49.460449, -44.806552, 51.328125, -44.759788, 52.272949, -44.93107, 53.459473"
    },
    {
      "from": 11,
      "to": 5,
      "distance": 289557.9,
      "road_type": "land",
      "road_name": "",
      "coords": "-44.93107, 53.459473, -44.681765, 54.228516, -43.99062, 55.151367, -43.546561, 55.546875, -43.038241, 55.393066"
    },
    {
      "from": 12,
      "to": 11,
      "distance": 424307.5,
      "road_type": "land",
      "road_name": "",
      "coords": "-45.982363, 58.688965, -45.74982, 57.216797, -45.380815, 55.480957, -44.93107, 53.459473"
    },
    {
      "from": 1,
      "to": 13,
      "distance": 572898.0,
      "road_type": "land",
      "road_name": "",
      "coords": "-40.246178, 64.973145, -41.538247, 66.796875, -43.353104, 67.104492, -44.707531, 67.758974"
    },
    {
      "from": 13,
      "to": 14,
      "distance": 274122.5,
      "road_type": "land",
      "road_name": "",
      "coords": "-44.707531, 67.758974, -45.609047, 68.203125, -46.764509, 69.609375"
    },
    {
      "from": 4,
      "to": 13,
      "distance": 346273.5,
      "road_type": "land",
      "road_name": "",
      "coords": "-44.59053, 63.413086, -44.603111, 65.34668, -44.556182, 66.906738, -44.707531, 67.758974"
    },
    {
      "from": 14,
      "to": 15,
      "distance": 892685.1,
      "road_type": "land",
      "road_name": "",
      "coords": "-46.764509, 69.609375, -48.218643, 72.333984, -49.089093, 74.619141, -50.057477, 77.475586, -50.338645, 80.332031"
    },
    {
      "from": 12,
      "to": 14,
      "distance": 843018.7,
      "road_type": "land",
      "road_name": "",
      "coords": "-45.982363, 58.688965, -46.221332, 62.907715, -46.463909, 66.269531, -46.764509, 69.609375"
    },
    {
      "from": 16,
      "to": 15,
      "distance": 247220.9,
      "road_type": "land",
      "road_name": "",
      "coords": "-50.401586, 83.803711, -50.478608, 82.045898, -50.338645, 80.332031"
    },
    {
      "from": 17,
      "to": 15,
      "distance": 204028.0,
      "road_type": "land",
      "road_name": "",
      "coords": "-51.399025, 77.958984, -50.338645, 80.332031"
    },
    {
      "from": 18,
      "to": 19,
      "distance": 458746.1,
      "road_type": "land",
      "road_name": "",
      "coords": "-46.650496, 48.603516, -47.425748, 48.823242, -48.353491, 49.108887, -49.049204, 49.21875, -49.735316, 49.482422, -50.694387, 49.152832"
    },
    {
      "from": 20,
      "to": 21,
      "distance": 793896.4,
      "road_type": "sea",
      "road_name": "",
      "coords": "-50.636559, 48.339844, -51.122416, 48.120117, -51.5341, 47.746582, -52.02325, 47.416992, -52.560545, 47.197266, -53.209876, 47.416992, -53.667745, 47.746582, -54.568743, 48.669844, -54.79727, 49.416504, -55.137654, 50.141602, -55.61184, 50.734863, -55.994477, 51.130371, -56.373365, 51.723633, -56.446266, 52.272949"
    },
    {
      "from": 22,
      "to": 21,
      "distance": 68503.0,
      "road_type": "sea",
      "road_name": "",
      "coords": "-55.851105, 52.558594, -56.446266, 52.272949"
    },
    {
      "from": 23,
      "to": 20,
      "distance": 454063.3,
      "road_type": "sea",
      "road_name": "",
      "coords": "-46.676581, 47.746582, -47.797265, 47.680664, -48.398614, 47.636719, -49.179919, 47.636719, -49.665618, 47.944336, -50.019687, 48.339844, -50.636559, 48.339844"
    },
    {
      "from": 19,
      "to": 20,
      "distance": 57659.2,
      "road_type": "sea",
      "road_name": "",
      "coords": "-50.694387, 49.152832, -50.636559, 48.339844"
    },
    {
      "from": 24,
      "to": 23,
      "distance": 247054.5,
      "road_type": "sea",
      "road_name": "",
      "coords": "-44.572786, 48.669434, -45.195179, 48.251953, -45.67292, 48.010254, -46.419813, 47.746582, -46.676581, 47.746582"
    },
    {
      "from": 18,
      "to": 23,
      "distance": 65457.5,
      "road_type": "sea",
      "road_name": "",
      "coords": "-46.650496, 48.603516, -46.676581, 47.746582"
    },
    {
      "from": 10,
      "to": 18,
      "distance": 216804.9,
      "road_type": "land",
      "road_name": "",
      "coords": "-44.794737, 49.460449, -46.650496, 48.603516"
    },
    {
      "from": 25,
      "to": 17,
      "distance": 397429.1,
      "road_type": "land",
      "road_name": "",
      "coords": "-54.315642, 76.816406, -53.88803, 76.113281, -53.170064, 75.915527, -52.520133, 76.223145, -51.982344, 76.750488, -51.399025, 77.958984"
    },
    {
      "from": 3,
      "to": 26,
      "distance": 179902.6,
      "road_type": "land",
      "road_name": "",
      "coords": "-42.716287, 59.282227, -43.70437, 59.853516, -44.241737, 59.985352"
    },
    {
      "from": 26,
      "to": 12,
      "distance": 219302.1,
      "road_type": "land",
      "road_name": "",
      "coords": "-44.241737, 59.985352, -45.00762, 59.545898, -45.982363, 58.688965"
    },
    {
      "from": 4,
      "to": 26,
      "distance": 276448.1,
      "road_type": "land",
      "road_name": "",
      "coords": "-44.59053, 63.413086, -44.571829, 61.831055, -44.241737, 59.985352"
    },
    {
      "from": 12,
      "to": 27,
      "distance": 256860.7,
      "road_type": "land",
      "road_name": "",
      "coords": "-45.982363, 58.688965, -47.175133, 55.810547"
    },
    {
      "from": 27,
      "to": 28,
      "distance": 194173.9,
      "road_type": "land",
      "road_name": "",
      "coords": "-47.175133, 55.810547, -48.879087, 55.239258"
    },
    {
      "from": 28,
      "to": 19,
      "distance": 500587.0,
      "road_type": "land",
      "road_name": "",
      "coords": "-48.879087, 55.239258, -49.380778, 54.656982, -49.921089, 53.778076, -50.427438, 52.23999, -50.615937, 50.460205, -50.694387, 49.152832"
    },
    {
      "from": 10,
      "to": 24,
      "distance": 67230.6,
      "road_type": "sea",
      "road_name": "",
      "coords": "-44.794737, 49.460449, -44.572786, 48.669434"
    },
    {
      "from": 29,
      "to": 24,
      "distance": 527288.8,
      "road_type": "sea",
      "road_name": "",
      "coords": "-43.019796, 54.580078, -43.371648, 51.16333, -43.67421, 50.020752, -44.227587, 48.966064, -44.572786, 48.669434"
    },
    {
      "from": 5,
      "to": 29,
      "distance": 66114.8,
      "road_type": "sea",
      "road_name": "",
      "coords": "-43.038241, 55.393066, -43.019796, 54.580078"
    },
    {
      "from": 1,
      "to": 29,
      "distance": 977679.2,
      "road_type": "sea",
      "road_name": "",
      "coords": "-40.246178, 64.973145, -40.061813, 64.160156, -40.39715, 62.512207, -40.930232, 60.292969, -41.36022, 58.930664, -42.016226, 57.414551, -42.13034, 55.964355, -42.244247, 55.151367, -42.63323, 54.580078, -43.019796, 54.580078"
    },
    {
      "from": 8,
      "to": 30,
      "distance": 194558.7,
      "road_type": "land",
      "road_name": "",
      "coords": "-10.597047, -75.849609, -10.542032, -76.190186, -10.477252, -76.514282, -10.428659, -76.832886, -10.353054, -77.211914, -10.229368, -77.585449"
    },
    {
      "from": 31,
      "to": 32,
      "distance": 643723.7,
      "road_type": "land",
      "road_name": "",
      "coords": "-47.25683, -130.830688, -45.274589, -122.957862"
    },
    {
      "from": 32,
      "to": 33,
      "distance": 916774.4,
      "road_type": "land",
      "road_name": "",
      "coords": "-45.274589, -122.957862, -44.298609, -120.849609, -43.091882, -118.652344, -41.631504, -116.762695, -39.858686, -114.543457"
    },
    {
      "from": 33,
      "to": 34,
      "distance": 637962.2,
      "road_type": "land",
      "road_name": "",
      "coords": "-39.858686, -114.543457, -38.678067, -113.422852, -37.398147, -112.851563, -36.308649, -112.5, -34.519117, -112.565918"
    },
    {
      "from": 19,
      "to": 22,
      "distance": 636059.5,
      "road_type": "land",
      "road_name": "",
      "coords": "-50.694387, 49.152832, -51.232229, 49.328613, -51.683797, 49.21875, -52.278955, 49.306641, -52.626929, 49.394531, -53.025027, 49.592285, -53.654418, 50.427246, -54.210384, 51.086426, -54.961216, 52.03125, -55.851105, 52.558594"
    },
    {
      "from": 31,
      "to": 35,
      "distance": 484917.8,
      "road_type": "land",
      "road_name": "",
      "coords": "-47.25683, -130.830688, -46.629096, -130.935059, -46.159551, -130.935059, -45.532332, -131.132813, -44.929144, -131.638184, -43.767039, -131.682129, -43.023322, -131.506348"
    },
    {
      "from": 35,
      "to": 33,
      "distance": 1564897.3,
      "road_type": "land",
      "road_name": "",
      "coords": "-43.023322, -131.506348, -42.51859, -130.429688, -41.818675, -129.265137, -41.292787, -128.38623, -40.995096, -127.463379, -40.362206, -124.541016, -40.09393, -123.684082, -39.790851, -122.277832, -39.790851, -120.651855, -39.807724, -119.179688, -39.824593, -117.70752, -39.790851, -116.542969, -39.31673, -115.158691, -39.858686, -114.543457"
    },
    {
      "from": 34,
      "to": 36,
      "distance": 1171437.6,
      "road_type": "land",
      "road_name": "",
      "coords": "-34.519117, -112.565918, -33.371181, -112.521973, -32.300951, -112.258301, -31.330555, -112.258301, -30.501547, -112.82959, -29.608148, -113.554688, -28.976086, -114.389648, -28.166031, -115.378418, -27.466777, -116.30127, -26.939402, -117.158203, -26.527506, -117.553711, -26.078217, -117.949219"
    },
    {
      "from": 36,
      "to": 37,
      "distance": 103855.3,
      "road_type": "land",
      "road_name": "",
      "coords": "-26.078217, -117.949219, -25.223396, -118.366699"
    },
    {
      "from": 37,
      "to": 38,
      "distance": 709782.3,
      "road_type": "land",
      "road_name": "",
      "coords": "-25.223396, -118.366699, -23.321595, -118.476563, -22.553046, -118.278809, -21.698593, -118.190918, -20.654201, -118.212891, -19.891965, -118.168945, -18.879617, -118.322754"
    },
    {
      "from": 39,
      "to": 37,
      "distance": 1076509.6,
      "road_type": "land",
      "road_name": "",
      "coords": "-25.470484, -128.71582, -25.538657, -127.727051, -25.558471, -126.826172, -25.558471, -125.551758, -24.9228, -124.277344, -24.763365, -123.574219, -24.463874, -122.189941, -24.643655, -120.915527, -25.223396, -118.366699"
    },
    {
      "from": 39,
      "to": 40,
      "distance": 712980.0,
      "road_type": "land",
      "road_name": "",
      "coords": "-25.470484, -128.71582, -24.119126, -128.056641, -22.991777, -127.705078, -21.528436, -127.177734, -20.70898, -126.474609, -19.808054, -125.679951"
    },
    {
      "from": 40,
      "to": 38,
      "distance": 786491.7,
      "road_type": "land",
      "road_name": "",
      "coords": "-19.808054, -125.679951, -19.305761, -123.837891, -19.139864, -122.695313, -18.80757, -121.069336, -18.80757, -119.838867, -18.879617, -118.322754"
    },
    {
      "from": 14,
      "to": 41,
      "distance": 269851.1,
      "road_type": "land",
      "road_name": "",
      "coords": "-46.764509, 69.609375, -48.043926, 68.950195, -49.090247, 68.598633"
    },
    {
      "from": 41,
      "to": 42,
      "distance": 310734.3,
      "road_type": "land",
      "road_name": "",
      "coords": "-49.090247, 68.598633, -48.859601, 66.621094, -48.661917, 64.401855"
    },
    {
      "from": 27,
      "to": 43,
      "distance": 319594.5,
      "road_type": "land",
      "road_name": "",
      "coords": "-47.175133, 55.810547, -47.512635, 57.832031, -47.867432, 59.941406"
    },
    {
      "from": 28,
      "to": 28,
      "distance": 368454.5,
      "road_type": "land",
      "road_name": "",
      "coords": "-48.879087, 55.239258, -48.569793, 56.865234, -48.395106, 58.535156, -47.867432, 59.941406"
    },
    {
      "from": 12,
      "to": 43,
      "distance": 231527.4,
      "road_type": "land",
      "road_name": "",
      "coords": "-45.982363, 58.688965, -46.885928, 59.458008, -47.867432, 59.941406"
    },
    {
      "from": 43,
      "to": 42,
      "distance": 373040.7,
      "road_type": "land",
      "road_name": "",
      "coords": "-47.867432, 59.941406, -47.958313, 60.578613, -47.855261, 61.347656, -47.870157, 62.402344, -47.899613, 63.347168, -48.237153, 63.984375, -48.661917, 64.401855"
    },
    {
      "from": 41,
      "to": 17,
      "distance": 713789.9,
      "road_type": "land",
      "road_name": "",
      "coords": "-49.090247, 68.598633, -49.720223, 70.356445, -50.172456, 71.850586, -50.620449, 73.740234, -50.925992, 75.234375, -51.399025, 77.958984"
    },
    {
      "from": 25,
      "to": 44,
      "distance": 716618.1,
      "road_type": "land",
      "road_name": "",
      "coords": "-54.315642, 76.816406, -54.657965, 75.585938, -54.974322, 74.729004, -54.974322, 73.520508, -54.923871, 72.663574, -54.746795, 71.762695, -54.479722, 69.697266, -54.198048, 68.356934, -53.888562, 67.565918, -53.61964, 66.445313"
    },
    {
      "from": 22,
      "to": 44,
      "distance": 941263.5,
      "road_type": "land",
      "road_name": "",
      "coords": "-55.851105, 52.558594, -55.859485, 54.624023, -55.896444, 55.678711, -55.847158, 56.821289, -55.785462, 58.095703, -55.450614, 60.556641, -55.350849, 60.996094, -54.924036, 61.896973, -54.594562, 62.709961, -54.223902, 63.742676, -53.862837, 65.170898, -53.61964, 66.445313"
    },
    {
      "from": 44,
      "to": 42,
      "distance": 573422.5,
      "road_type": "land",
      "road_name": "",
      "coords": "-53.61964, 66.445313, -52.207957, 66.181641, -51.475266, 65.610352, -50.395803, 65.170898, -49.54834, 64.6875, -48.661917, 64.401855"
    },
    {
      "from": 25,
      "to": 45,
      "distance": 303850.8,
      "road_type": "sea",
      "road_name": "",
      "coords": "-54.315642, 76.816406, -53.952205, 77.893066, -53.692932, 78.640137, -53.353475, 79.672852, -53.143224, 80.266113, -52.812636, 80.57373"
    },
    {
      "from": 16,
      "to": 45,
      "distance": 449520.9,
      "road_type": "sea",
      "road_name": "",
      "coords": "-50.401586, 83.803711, -50.664402, 84.638672, -51.121538, 84.199219, -51.341567, 83.671875, -51.64239, 83.210449, -52.062914, 82.661133, -52.42598, 82.001953, -52.79936, 81.386719, -52.812636, 80.57373"
    },
    {
      "from": 17,
      "to": 45,
      "distance": 252535.7,
      "road_type": "sea",
      "road_name": "",
      "coords": "-51.399025, 77.958984, -52.062914, 78.354492, -52.43937, 79.16748, -52.653055, 79.716797, -52.812636, 80.57373"
    },
    {
      "from": 39,
      "to": 46,
      "distance": 1026039.5,
      "road_type": "land",
      "road_name": "",
      "coords": "-25.470484, -128.71582, -25.28403, -129.572754, -25.28403, -130.539551, -25.244308, -131.638184, -25.224442, -132.868652, -25.204573, -134.077148, -25.28403, -135.615234, -25.26417, -136.955566, -25.203624, -138.88916"
    },
    {
      "from": 46,
      "to": 47,
      "distance": 739736.2,
      "road_type": "land",
      "road_name": "",
      "coords": "-25.203624, -138.88916, -25.581162, -139.614258, -26.01616, -140.317383, -26.587109, -141.262207, -27.116137, -141.987305, -27.486925, -142.77832, -27.895296, -143.547363, -28.263452, -144.074707, -28.803684, -145.151367"
    },
    {
      "from": 47,
      "to": 48,
      "distance": 645155.3,
      "road_type": "land",
      "road_name": "",
      "coords": "-28.803684, -145.151367, -28.97674, -146.008301, -29.321984, -146.821289, -29.856713, -147.216797, -30.502192, -147.524414, -31.368705, -147.963867, -32.208721, -148.139648, -32.856758, -148.07373, -33.298413, -148.227539"
    },
    {
      "from": 49,
      "to": 49,
      "distance": 724112.6,
      "road_type": "land",
      "road_name": "",
      "coords": "-33.266278, -139.817505, -32.743552, -140.427246, -32.516984, -140.740356, -32.266633, -141.119385, -32.062132, -141.448975, -31.773193, -141.992798, -31.427146, -142.459717, -30.833393, -143.140869, -30.606835, -143.371582, -30.256519, -143.822021, -30.076139, -144.261475, -29.676236, -144.711914, -29.447003, -144.942627, -28.803684, -145.151367"
    },
    {
      "from": 50,
      "to": 46,
      "distance": 712237.2,
      "road_type": "land",
      "road_name": "",
      "coords": "-24.36598, -145.84559, -24.443652, -144.316406, -24.503617, -142.756348, -24.623462, -141.394043, -25.203624, -138.88916"
    },
    {
      "from": 50,
      "to": 47,
      "distance": 561710.0,
      "road_type": "land",
      "road_name": "",
      "coords": "-24.36598, -145.84559, -25.180177, -146.096191, -25.774952, -146.491699, -26.288026, -146.57959, -26.681162, -146.403809, -27.05339, -146.030273, -27.619151, -145.568848, -27.930053, -145.129395, -28.803684, -145.151367"
    },
    {
      "from": 48,
      "to": 51,
      "distance": 642867.4,
      "road_type": "land",
      "road_name": "",
      "coords": "-33.298413, -148.227539, -33.609906, -148.73291, -33.829109, -149.699707, -33.865589, -150.644531, -33.883823, -151.347656, -34.120508, -152.53418, -34.356532, -153.544922, -34.593566, -154.939898"
    },
    {
      "from": 40,
      "to": 52,
      "distance": 961551.5,
      "road_type": "land",
      "road_name": "",
      "coords": "-19.808054, -125.679951, -18.447053, -125.463867, -16.940669, -125.463867, -15.929597, -125.727539, -15.040701, -125.947266, -13.892396, -126.342773, -12.866864, -126.870117, -11.525221, -127.437305"
    },
    {
      "from": 48,
      "to": 49,
      "distance": 798203.5,
      "road_type": "land",
      "road_name": "",
      "coords": "-33.298413, -148.227539, -33.021494, -146.337891, -32.984658, -144.887695, -32.800248, -143.745117, -32.800248, -142.514648, -32.800248, -141.37207, -33.266278, -139.817505"
    },
    {
      "from": 49,
      "to": 46,
      "distance": 957507.5,
      "road_type": "land",
      "road_name": "",
      "coords": "-33.266278, -139.817505, -32.598559, -140.053711, -32.153415, -140.273438, -31.537778, -140.449219, -30.880365, -140.471191, -30.047465, -140.427246, -29.341601, -140.251465, -28.553681, -139.54834, -28.205882, -139.020996, -27.584773, -139.020996, -27.136163, -138.999023, -26.371357, -138.977051, -25.203624, -138.88916"
    },
    {
      "from": 49,
      "to": 53,
      "distance": 71977.5,
      "road_type": "sea",
      "road_name": "",
      "coords": "-33.266278, -139.817505, -33.599943, -139.152832"
    },
    {
      "from": 39,
      "to": 54,
      "distance": 58065.3,
      "road_type": "sea",
      "road_name": "",
      "coords": "-25.470484, -128.71582, -25.972569, -128.875122"
    },
    {
      "from": 54,
      "to": 53,
      "distance": 1345605.7,
      "road_type": "sea",
      "road_name": "",
      "coords": "-25.972569, -128.875122, -26.558474, -130.023193, -26.960471, -130.913086, -27.214655, -132.044678, -27.478004, -132.780762, -27.973724, -133.417969, -28.650427, -134.176025, -29.03517, -134.714355, -29.771768, -135.670166, -30.644802, -136.636963, -31.528747, -137.526855, -32.265232, -138.087158, -32.931297, -138.55957, -33.599943, -139.152832"
    },
    {
      "from": 31,
      "to": 55,
      "distance": 90791.4,
      "road_type": "sea",
      "road_name": "",
      "coords": "-47.25683, -130.830688, -47.271662, -132.033691"
    },
    {
      "from": 55,
      "to": 53,
      "distance": 1749376.9,
      "road_type": "sea",
      "road_name": "",
      "coords": "-47.271662, -132.033691, -46.467117, -132.297363, -45.705533, -132.802734, -45.181649, -133.417969, -44.652899, -133.681641, -44.056186, -133.945313, -43.197777, -134.58252, -42.667163, -134.956055, -42.099399, -135.065918, -41.279412, -134.604492, -40.549191, -134.472656, -39.962584, -134.055176, -39.557404, -133.835449, -33.599943, -139.152832"
    },
    {
      "from": 34,
      "to": 56,
      "distance": 433806.3,
      "road_type": "land",
      "road_name": "",
      "coords": "-34.519117, -112.565918, -35.388287, -111.533203, -36.065767, -110.588379, -36.384663, -110.170898, -37.581138, -110.041308"
    },
    {
      "from": 56,
      "to": 33,
      "distance": 509665.3,
      "road_type": "land",
      "road_name": "",
      "coords": "-37.581138, -110.041308, -38.132478, -110.170898, -38.477154, -110.43457, -38.854402, -110.698242, -39.110476, -111.269531, -39.3826, -111.796875, -39.653667, -112.543945, -39.755045, -113.466797, -39.858686, -114.543457"
    },
    {
      "from": 1,
      "to": 57,
      "distance": 495064.3,
      "road_type": "land",
      "road_name": "",
      "coords": "-40.246178, 64.973145, -39.931384, 65.874023, -39.593746, 66.950684, -39.288458, 67.91748, -39.152345, 68.862305, -39.050087, 69.631348, -38.925756, 70.444336"
    },
    {
      "from": 58,
      "to": 59,
      "distance": 64373.5,
      "road_type": "land",
      "road_name": "",
      "coords": "-0.829334, -105.809326, -0.724187, -105.639038, -0.658306, -105.474243, -0.620418, -105.276489"
    },
    {
      "from": 58,
      "to": 58,
      "distance": 48407.5,
      "road_type": "land",
      "road_name": "",
      "coords": "-1.081834, -105.485229, -0.954759, -105.545654, -0.883393, -105.650024, -0.829334, -105.809326"
    },
    {
      "from": 36,
      "to": 60,
      "distance": 964043.4,
      "road_type": "land",
      "road_name": "",
      "coords": "-26.078217, -117.949219, -25.12318, -116.147461, -23.844059, -113.818359, -23.361074, -112.456055, -22.471039, -110.874023, -21.560385, -109.929199"
    },
    {
      "from": 60,
      "to": 61,
      "distance": 1045340.3,
      "road_type": "land",
      "road_name": "",
      "coords": "-21.560385, -109.929199, -21.084274, -107.446289, -20.427116, -106.391602, -19.145917, -105.556641, -17.771059, -104.765625, -15.115754, -103.888758"
    },
    {
      "from": 38,
      "to": 61,
      "distance": 1611002.9,
      "road_type": "land",
      "road_name": "",
      "coords": "-18.879617, -118.322754, -18.730461, -116.499023, -18.188841, -114.873047, -17.645533, -113.730469, -16.890556, -111.796875, -16.005925, -109.6875, -15.286904, -107.226563, -15.202148, -106.040039, -15.115754, -103.888758"
    },
    {
      "from": 59,
      "to": 62,
      "distance": 136065.4,
      "road_type": "land",
      "road_name": "",
      "coords": "-0.620418, -105.276489, -0.482622, -105.320435, -0.306933, -105.375366, -0.043395, -105.430298, 0.220144, -105.419312, 0.412306, -105.408325, 0.570682, -105.3479"
    },
    {
      "from": 59,
      "to": 59,
      "distance": 41798.4,
      "road_type": "sea",
      "road_name": "",
      "coords": "-0.620418, -105.276489, -0.521053, -104.91394"
    },
    {
      "from": 62,
      "to": 62,
      "distance": 54497.7,
      "road_type": "sea",
      "road_name": "",
      "coords": "0.570682, -105.3479, 0.719753, -104.880981"
    },
    {
      "from": 62,
      "to": 59,
      "distance": 142211.3,
      "road_type": "sea",
      "road_name": "",
      "coords": "0.719753, -104.880981, 0.566032, -104.80957, 0.406816, -104.782104, 0.209164, -104.760132, 0.049942, -104.782104, -0.147712, -104.848022, -0.295952, -104.886475, -0.521053, -104.91394"
    },
    {
      "from": 63,
      "to": 64,
      "distance": 658251.6,
      "road_type": "sea",
      "road_name": "",
      "coords": "-14.827156, -85.429688, -15.155672, -85.880127, -15.346366, -86.583252, -15.28282, -87.440186, -15.028447, -88.253174, -14.858696, -88.934326, -14.62507, -90.0, -14.327369, -91.2854"
    },
    {
      "from": 65,
      "to": 64,
      "distance": 187653.8,
      "road_type": "sea",
      "road_name": "",
      "coords": "-13.550387, -92.828979, -14.327369, -91.2854"
    },
    {
      "from": 64,
      "to": 66,
      "distance": 996355.8,
      "road_type": "sea",
      "road_name": "",
      "coords": "-14.327369, -91.2854, -15.144313, -90.725098, -15.990544, -90.076904, -17.106278, -89.165039, -17.776735, -88.615723, -18.111029, -88.077393, -18.455102, -87.363281, -18.663298, -86.539307, -19.037404, -85.869141, -19.783081, -85.473633, -20.593899, -85.03418"
    },
    {
      "from": 61,
      "to": 67,
      "distance": 371627.4,
      "road_type": "land",
      "road_name": "",
      "coords": "-15.115754, -103.888758, -15.092832, -103.304443, -15.071627, -102.88147, -15.066325, -102.442017, -15.02921, -101.469727, -14.997392, -101.090698, -15.007998, -100.739136, -14.997793, -100.431519"
    },
    {
      "from": 67,
      "to": 68,
      "distance": 362500.3,
      "road_type": "land",
      "road_name": "",
      "coords": "-14.997793, -100.431519, -14.944351, -100.123901, -14.864766, -99.607544, -14.726749, -99.09668, -14.572703, -98.613281, -14.381324, -98.118896, -14.184459, -97.783813, -14.040692, -97.597046, -13.839985, -97.338867"
    },
    {
      "from": 68,
      "to": 65,
      "distance": 491450.3,
      "road_type": "land",
      "road_name": "",
      "coords": "-13.839985, -97.338867, -13.73148, -97.146606, -13.699477, -96.756592, -13.635457, -95.921631, -13.614114, -95.097656, -13.614114, -94.702148, -13.608778, -93.790283, -13.608778, -93.328857, -13.571421, -93.043213, -13.550387, -92.828979"
    },
    {
      "from": 69,
      "to": 70,
      "distance": 581923.0,
      "road_type": "land",
      "road_name": "",
      "coords": "-24.507425, -95.734863, -24.359913, -92.197266, -23.30223, -90.32959"
    },
    {
      "from": 69,
      "to": 71,
      "distance": 475982.7,
      "road_type": "land",
      "road_name": "",
      "coords": "-24.507425, -95.734863, -26.462452, -96.943359, -28.379817, -97.734375"
    },
    {
      "from": 69,
      "to": 72,
      "distance": 611079.0,
      "road_type": "land",
      "road_name": "",
      "coords": "-24.507425, -95.734863, -23.718097, -96.811523, -22.546762, -99.18457, -21.41372, -100.634766"
    },
    {
      "from": 73,
      "to": 74,
      "distance": 171072.7,
      "road_type": "land",
      "road_name": "",
      "coords": "0.482573, -108.621434, 0.588689, -108.336182, 0.70398, -108.07251, 0.73692, -107.874756, 0.813778, -107.506714, 0.851998, -107.138672"
    },
    {
      "from": 73,
      "to": 73,
      "distance": 53918.7,
      "road_type": "land",
      "road_name": "",
      "coords": "0.482573, -108.621434, 0.38006, -108.462524, 0.303196, -108.17688"
    },
    {
      "from": 73,
      "to": 75,
      "distance": 60619.0,
      "road_type": "land",
      "road_name": "",
      "coords": "0.303196, -108.17688, 0.314177, -107.86377, 0.291095, -107.633057"
    },
    {
      "from": 73,
      "to": 76,
      "distance": 52251.5,
      "road_type": "land",
      "road_name": "",
      "coords": "0.303196, -108.17688, 0.089071, -108.149414, -0.164721, -108.138428"
    },
    {
      "from": 70,
      "to": 77,
      "distance": 1181542.3,
      "road_type": "land",
      "road_name": "",
      "coords": "-23.30223, -90.32959, -24.211609, -90.483398, -24.970452, -90.527344, -25.328286, -90.615234, -25.803757, -90.725098, -25.98157, -91.582031, -26.040781, -92.307129, -26.316705, -93.076172, -26.552689, -93.823242, -27.042763, -95.031738, -28.480797, -96.28418, -29.115891, -96.591797, -30.600502, -96.877441"
    },
    {
      "from": 70,
      "to": 72,
      "distance": 1116714.9,
      "road_type": "land",
      "road_name": "",
      "coords": "-23.30223, -90.32959, -22.95741, -91.494141, -22.146127, -92.724609, -21.616262, -93.669434, -21.493707, -94.921875, -21.411947, -95.756836, -21.350597, -97.316895, -21.37105, -98.481445, -21.411947, -99.492188, -21.41372, -100.634766"
    },
    {
      "from": 78,
      "to": 74,
      "distance": 74944.7,
      "road_type": "land",
      "road_name": "",
      "coords": "1.707887, -106.567383, 1.549332, -106.693726, 1.384674, -106.748657, 1.103849, -106.847534"
    },
    {
      "from": 79,
      "to": 78,
      "distance": 94375.2,
      "road_type": "land",
      "road_name": "",
      "coords": "1.241284, -105.858765, 1.385188, -106.067505, 1.483985, -106.221313, 1.615706, -106.408081, 1.707887, -106.567383"
    },
    {
      "from": 80,
      "to": 81,
      "distance": 109950.9,
      "road_type": "land",
      "road_name": "",
      "coords": "-0.175377, -106.303711, 0.001016, -106.204834, 0.121805, -106.122437, 0.259064, -106.089478, 0.390832, -106.067505, 0.522598, -106.12793, 0.713983, -106.237793"
    },
    {
      "from": 80,
      "to": 82,
      "distance": 75166.1,
      "road_type": "land",
      "road_name": "",
      "coords": "-0.175377, -106.303711, -0.344878, -106.380615, -0.564488, -106.479492, -0.785173, -106.594849"
    },
    {
      "from": 32,
      "to": 83,
      "distance": 474559.1,
      "road_type": "land",
      "road_name": "",
      "coords": "-45.274589, -122.957862, -45.334117, -121.59668, -45.318676, -120.388184, -45.287783, -118.608398, -45.575399, -116.938477"
    },
    {
      "from": 32,
      "to": 35,
      "distance": 733646.3,
      "road_type": "land",
      "road_name": "",
      "coords": "-45.274589, -122.957862, -44.822358, -124.365234, -44.290297, -125.507813, -43.785091, -127.441406, -43.339503, -129.506836, -43.195578, -130.583496, -43.023322, -131.506348"
    },
    {
      "from": 84,
      "to": 76,
      "distance": 73567.2,
      "road_type": "land",
      "road_name": "",
      "coords": "-0.48873, -107.561646, -0.339388, -107.836304, -0.164721, -108.138428"
    },
    {
      "from": 84,
      "to": 82,
      "distance": 113705.0,
      "road_type": "land",
      "road_name": "",
      "coords": "-0.48873, -107.561646, -0.575468, -107.325439, -0.586448, -107.072754, -0.663309, -106.858521, -0.785173, -106.594849"
    },
    {
      "from": 85,
      "to": 76,
      "distance": 126057.1,
      "road_type": "land",
      "road_name": "",
      "coords": "-0.005349, -107.017822, -0.038185, -107.330933, -0.093089, -107.616577, -0.10407, -107.825317, -0.164721, -108.138428"
    },
    {
      "from": 86,
      "to": 76,
      "distance": 101153.7,
      "road_type": "land",
      "road_name": "",
      "coords": "-1.049105, -108.308716, -0.806816, -108.308716, -0.620157, -108.264771, -0.42251, -108.237305, -0.164721, -108.138428"
    },
    {
      "from": 82,
      "to": 86,
      "distance": 193296.9,
      "road_type": "land",
      "road_name": "",
      "coords": "-0.785173, -106.594849, -0.834265, -106.847534, -0.867204, -107.08374, -0.894653, -107.325439, -0.916612, -107.567139, -0.94406, -107.786865, -0.960529, -107.979126, -0.982488, -108.110962, -1.049105, -108.308716"
    },
    {
      "from": 85,
      "to": 84,
      "distance": 82593.7,
      "road_type": "land",
      "road_name": "",
      "coords": "-0.005349, -107.017822, -0.169955, -107.171631, -0.307214, -107.276001, -0.389569, -107.347412, -0.48873, -107.561646"
    },
    {
      "from": 84,
      "to": 86,
      "distance": 103878.3,
      "road_type": "land",
      "road_name": "",
      "coords": "-0.48873, -107.561646, -0.680547, -107.825317, -0.806816, -108.006592, -1.049105, -108.308716"
    },
    {
      "from": 79,
      "to": 79,
      "distance": 39125.1,
      "road_type": "sea",
      "road_name": "",
      "coords": "1.241284, -105.858765, 1.461307, -105.584106"
    },
    {
      "from": 62,
      "to": 79,
      "distance": 115728.2,
      "road_type": "sea",
      "road_name": "",
      "coords": "0.719753, -104.880981, 0.857488, -104.952393, 1.038647, -105.089722, 1.230773, -105.265503, 1.351532, -105.380859, 1.461307, -105.584106"
    },
    {
      "from": 74,
      "to": 74,
      "distance": 42801.4,
      "road_type": "land",
      "road_name": "",
      "coords": "1.103849, -106.847534, 0.851998, -107.138672"
    },
    {
      "from": 74,
      "to": 75,
      "distance": 83484.1,
      "road_type": "land",
      "road_name": "",
      "coords": "0.851998, -107.138672, 0.676321, -107.325439, 0.495147, -107.446289, 0.291095, -107.633057"
    },
    {
      "from": 75,
      "to": 76,
      "distance": 76065.8,
      "road_type": "land",
      "road_name": "",
      "coords": "0.291095, -107.633057, 0.099843, -107.896729, -0.164721, -108.138428"
    },
    {
      "from": 75,
      "to": 85,
      "distance": 76661.1,
      "road_type": "land",
      "road_name": "",
      "coords": "0.291095, -107.633057, 0.209651, -107.369385, 0.138276, -107.221069, -0.005349, -107.017822"
    },
    {
      "from": 79,
      "to": 62,
      "distance": 97123.4,
      "road_type": "land",
      "road_name": "",
      "coords": "1.241284, -105.858765, 1.115499, -105.748901, 1.027668, -105.661011, 0.912385, -105.496216, 0.74769, -105.380859, 0.570682, -105.3479"
    },
    {
      "from": 81,
      "to": 79,
      "distance": 72922.0,
      "road_type": "land",
      "road_name": "",
      "coords": "0.713983, -106.237793, 0.884937, -106.12793, 1.038647, -106.056519, 1.241284, -105.858765"
    },
    {
      "from": 74,
      "to": 79,
      "distance": 111328.0,
      "road_type": "land",
      "road_name": "",
      "coords": "1.103849, -106.847534, 1.170392, -106.572876, 1.208817, -106.364136, 1.230773, -106.116943, 1.241284, -105.858765"
    },
    {
      "from": 81,
      "to": 74,
      "distance": 82009.9,
      "road_type": "land",
      "road_name": "",
      "coords": "0.713983, -106.237793, 0.805803, -106.331177, 0.910109, -106.435547, 1.008923, -106.578369, 1.103849, -106.847534"
    },
    {
      "from": 85,
      "to": 74,
      "distance": 126694.0,
      "road_type": "land",
      "road_name": "",
      "coords": "-0.005349, -107.017822, 0.245807, -107.028809, 0.388556, -107.028809, 0.542282, -106.990356, 0.728944, -106.973877, 0.877171, -106.951904, 1.103849, -106.847534"
    },
    {
      "from": 52,
      "to": 87,
      "distance": 996574.4,
      "road_type": "land",
      "road_name": "",
      "coords": "-11.525221, -127.437305, -11.743067, -125.639648, -12.086882, -124.189453, -13.030063, -121.68457, -13.969665, -120.366211, -14.779314, -119.040234"
    },
    {
      "from": 87,
      "to": 61,
      "distance": 1700298.1,
      "road_type": "land",
      "road_name": "",
      "coords": "-14.779314, -119.040234, -14.565621, -116.71875, -14.26784, -114.521484, -14.225268, -112.719727, -14.012286, -110.742188, -13.628421, -107.841797, -13.671104, -105.820313, -14.097502, -104.897461, -15.115754, -103.888758"
    },
    {
      "from": 87,
      "to": 38,
      "distance": 471829.8,
      "road_type": "land",
      "road_name": "",
      "coords": "-14.779314, -119.040234, -16.343613, -118.432617, -17.394428, -118.168945, -18.879617, -118.322754"
    },
    {
      "from": 88,
      "to": 33,
      "distance": 621988.6,
      "road_type": "land",
      "road_name": "",
      "coords": "-45.341785, -114.98291, -43.827283, -114.257813, -42.96559, -114.213867, -41.830364, -114.213867, -40.840997, -114.257813, -39.858686, -114.543457"
    },
    {
      "from": 31,
      "to": 83,
      "distance": 1099117.2,
      "road_type": "land",
      "road_name": "",
      "coords": "-47.25683, -130.830688, -47.300538, -127.177734, -47.181257, -124.145508, -47.181257, -121.59668, -46.580821, -119.223633, -46.004179, -118.081055, -45.575399, -116.938477"
    },
    {
      "from": 83,
      "to": 88,
      "distance": 154716.3,
      "road_type": "land",
      "road_name": "",
      "coords": "-45.575399, -116.938477, -45.341785, -114.98291"
    },
    {
      "from": 56,
      "to": 89,
      "distance": 1311853.2,
      "road_type": "land",
      "road_name": "",
      "coords": "-37.581138, -110.041308, -37.539916, -106.259766, -36.628904, -104.589844, -34.485163, -101.601562, -33.53855, -100.59082, -32.359116, -99.667969, -31.088896, -99.667969"
    },
    {
      "from": 34,
      "to": 89,
      "distance": 1271123.4,
      "road_type": "land",
      "road_name": "",
      "coords": "-34.519117, -112.565918, -33.90388, -110.478516, -32.9508, -107.666016, -32.655447, -105.820313, -32.210584, -104.326172, -32.06181, -102.612305, -31.464294, -100.766602, -31.088896, -99.667969"
    },
    {
      "from": 89,
      "to": 77,
      "distance": 275866.7,
      "road_type": "land",
      "road_name": "",
      "coords": "-31.088896, -99.667969, -30.636453, -98.261719, -30.600502, -96.877441"
    },
    {
      "from": 77,
      "to": 90,
      "distance": 89176.9,
      "road_type": "sea",
      "road_name": "",
      "coords": "-30.600502, -96.877441, -30.918196, -96.020508"
    },
    {
      "from": 90,
      "to": 66,
      "distance": 1719005.7,
      "road_type": "sea",
      "road_name": "",
      "coords": "-30.918196, -96.020508, -30.009581, -95.339355, -29.360887, -94.416504, -28.380069, -92.219238, -28.051085, -91.318359, -27.701648, -90.307617, -27.312069, -89.230957, -26.803567, -87.692871, -26.23369, -86.879883, -25.561987, -86.418457, -24.786844, -86.066895, -22.635492, -85.78125, -21.618299, -85.385742, -20.593899, -85.03418"
    },
    {
      "from": 66,
      "to": 63,
      "distance": 647334.1,
      "road_type": "sea",
      "road_name": "",
      "coords": "-20.593899, -85.03418, -19.645325, -85.187988, -17.919658, -85.407715, -16.766706, -85.429688, -16.050427, -85.605469, -14.827156, -85.429688"
    },
    {
      "from": 77,
      "to": 71,
      "distance": 260483.2,
      "road_type": "land",
      "road_name": "",
      "coords": "-30.600502, -96.877441, -29.761797, -97.207031, -28.379817, -97.734375"
    },
    {
      "from": 71,
      "to": 72,
      "distance": 851531.4,
      "road_type": "land",
      "road_name": "",
      "coords": "-28.379817, -97.734375, -27.136055, -98.305664, -26.03627, -99.360352, -24.527115, -100.107422, -23.322666, -100.634766, -22.432378, -100.722656, -21.41372, -100.634766"
    },
    {
      "from": 60,
      "to": 72,
      "distance": 986221.3,
      "road_type": "land",
      "road_name": "",
      "coords": "-21.560385, -109.929199, -22.309966, -107.841797, -22.350595, -106.875, -22.065941, -105.358887, -22.025229, -103.842773, -21.821495, -102.414551, -21.73992, -101.535645, -21.41372, -100.634766"
    },
    {
      "from": 72,
      "to": 61,
      "distance": 824775.1,
      "road_type": "land",
      "road_name": "",
      "coords": "-21.41372, -100.634766, -20.757442, -100.546875, -18.815042, -101.184082, -17.667876, -101.469727, -16.429106, -102.23877, -15.880653, -102.612305, -15.115754, -103.888758"
    },
    {
      "from": 82,
      "to": 82,
      "distance": 42468.8,
      "road_type": "land",
      "road_name": "",
      "coords": "-1.070691, -106.342163, -0.938887, -106.473999, -0.785173, -106.594849"
    },
    {
      "from": 82,
      "to": 58,
      "distance": 92475.0,
      "road_type": "land",
      "road_name": "",
      "coords": "-0.785173, -106.594849, -0.708314, -106.430054, -0.686354, -106.243286, -0.708314, -106.072998, -0.829334, -105.809326"
    },
    {
      "from": 82,
      "to": 85,
      "distance": 98966.5,
      "road_type": "land",
      "road_name": "",
      "coords": "-0.785173, -106.594849, -0.598513, -106.677246, -0.439297, -106.743164, -0.258117, -106.864014, -0.005349, -107.017822"
    },
    {
      "from": 58,
      "to": 80,
      "distance": 91853.5,
      "road_type": "land",
      "road_name": "",
      "coords": "-0.829334, -105.809326, -0.64778, -105.957642, -0.488566, -106.083984, -0.312878, -106.166382, -0.175377, -106.303711"
    },
    {
      "from": 80,
      "to": 85,
      "distance": 84952.5,
      "road_type": "land",
      "road_name": "",
      "coords": "-0.175377, -106.303711, -0.065811, -106.430054, -0.010907, -106.594849, -0.005416, -106.765137, -0.005349, -107.017822"
    },
    {
      "from": 91,
      "to": 80,
      "distance": 99989.9,
      "road_type": "land",
      "road_name": "",
      "coords": "-0.043395, -105.430298, -0.065811, -105.5896, -0.153657, -105.776367, -0.19758, -106.034546, -0.175377, -106.303711"
    },
    {
      "from": 62,
      "to": 81,
      "distance": 100771.4,
      "road_type": "land",
      "road_name": "",
      "coords": "0.570682, -105.3479, 0.604008, -105.474243, 0.609499, -105.704956, 0.675379, -105.924683, 0.713983, -106.237793"
    },
    {
      "from": 81,
      "to": 85,
      "distance": 120366.4,
      "road_type": "land",
      "road_name": "",
      "coords": "0.713983, -106.237793, 0.604008, -106.386108, 0.450283, -106.484985, 0.274594, -106.660767, 0.21969, -106.814575, -0.005349, -107.017822"
    },
    {
      "from": 59,
      "to": 58,
      "distance": 58940.7,
      "road_type": "land",
      "road_name": "",
      "coords": "-0.620418, -105.276489, -0.779405, -105.287476, -0.911161, -105.325928, -1.081834, -105.485229"
    },
    {
      "from": 9,
      "to": 92,
      "distance": 283183.3,
      "road_type": "land",
      "road_name": "",
      "coords": "-12.599717, -75.344238, -12.574672, -75.706787, -12.435308, -76.080322, -12.295869, -76.387939, -12.349508, -76.761475, -12.413861, -77.244873, -12.413861, -77.684326, -12.381686, -77.88208"
    },
    {
      "from": 92,
      "to": 93,
      "distance": 664151.1,
      "road_type": "land",
      "road_name": "",
      "coords": "-12.381686, -77.88208, -12.26368, -78.354492, -12.349508, -78.717041, -12.488918, -78.980713, -12.756803, -79.266357, -12.949506, -79.49707, -13.22759, -79.881592, -13.377196, -80.189209, -13.462644, -80.628662, -13.558737, -81.079102, -13.622777, -81.397705, -13.718805, -81.815186, -14.272854, -82.661133, -14.421791, -82.880859, -14.694457, -83.298674"
    },
    {
      "from": 30,
      "to": 94,
      "distance": 84193.9,
      "road_type": "land",
      "road_name": "",
      "coords": "-10.229368, -77.585449, -10.478514, -77.76123, -10.877768, -77.980957"
    },
    {
      "from": 94,
      "to": 92,
      "distance": 167574.4,
      "road_type": "land",
      "road_name": "",
      "coords": "-10.877768, -77.980957, -12.381686, -77.88208"
    },
    {
      "from": 93,
      "to": 95,
      "distance": 84118.6,
      "road_type": "sea",
      "road_name": "",
      "coords": "-14.694457, -83.298674, -15.44195, -83.419189"
    },
    {
      "from": 93,
      "to": 96,
      "distance": 293923.8,
      "road_type": "land",
      "road_name": "",
      "coords": "-14.694457, -83.298674, -14.587722, -83.353271, -14.651474, -83.446655, -14.593036, -83.688354, -14.518637, -83.886108, -14.38572, -84.226685, -14.215471, -84.578247, -14.066398, -84.852905, -13.831944, -85.24292, -13.778626, -85.517578, -13.767961, -85.731812"
    },
    {
      "from": 96,
      "to": 96,
      "distance": 60194.3,
      "road_type": "land",
      "road_name": "",
      "coords": "-13.767961, -85.731812, -13.831944, -85.880127, -13.86926, -86.011963, -13.86926, -86.121826, -13.965648, -86.231689"
    },
    {
      "from": 96,
      "to": 63,
      "distance": 128987.4,
      "road_type": "sea",
      "road_name": "",
      "coords": "-13.965648, -86.231689, -14.827156, -85.429688"
    },
    {
      "from": 63,
      "to": 95,
      "distance": 226986.1,
      "road_type": "sea",
      "road_name": "",
      "coords": "-14.827156, -85.429688, -15.187283, -84.517822, -15.44195, -83.419189"
    },
    {
      "from": 9,
      "to": 97,
      "distance": 105266.2,
      "road_type": "sea",
      "road_name": "",
      "coords": "-12.599717, -75.344238, -13.314275, -74.707031"
    },
    {
      "from": 98,
      "to": 67,
      "distance": 521423.4,
      "road_type": "land",
      "road_name": "",
      "coords": "-18.041333, -97.283936, -17.9754, -97.679443, -17.881374, -98.10791, -17.578064, -98.547363, -17.211322, -98.723145, -16.791297, -98.964844, -16.380875, -99.18457, -15.842867, -99.360352, -15.430477, -99.547119, -15.112693, -99.821777, -15.050046, -100.079956, -14.997793, -100.431519"
    },
    {
      "from": 98,
      "to": 99,
      "distance": 66543.1,
      "road_type": "sea",
      "road_name": "",
      "coords": "-18.041333, -97.283936, -18.621686, -97.130127"
    },
    {
      "from": 98,
      "to": 65,
      "distance": 693703.2,
      "road_type": "land",
      "road_name": "",
      "coords": "-18.041333, -97.283936, -17.787221, -96.899414, -17.483752, -96.569824, -17.064343, -96.229248, -16.654509, -95.74585, -16.138347, -95.383301, -15.694847, -94.954834, -15.335114, -94.63623, -14.879271, -94.196777, -14.507521, -93.845215, -14.124498, -93.35083, -13.86879, -93.087158, -13.550387, -92.828979"
    },
    {
      "from": 99,
      "to": 64,
      "distance": 791516.3,
      "road_type": "sea",
      "road_name": "",
      "coords": "-18.621686, -97.130127, -18.382761, -96.427002, -17.620428, -95.163574, -17.033425, -94.383545, -16.307619, -93.482666, -15.822241, -92.8125, -15.197986, -92.06543, -14.327369, -91.2854"
    },
    {
      "from": 99,
      "to": 100,
      "distance": 1053385.4,
      "road_type": "sea",
      "road_name": "",
      "coords": "-18.621686, -97.130127, -18.944525, -96.350098, -19.203966, -94.229736, -19.297265, -93.14209, -19.297265, -91.746826, -19.286901, -90.406494, -19.120989, -89.384766, -18.726282, -88.703613, -18.455102, -87.363281"
    },
    {
      "from": 101,
      "to": 102,
      "distance": 214479.0,
      "road_type": "land",
      "road_name": "",
      "coords": "-8.405997, -91.40625, -8.253892, -91.933594, -8.145209, -92.504883, -8.058242, -93.317871"
    },
    {
      "from": 102,
      "to": 103,
      "distance": 402680.8,
      "road_type": "land",
      "road_name": "",
      "coords": "-8.058242, -93.317871, -8.210422, -94.086914, -8.362545, -94.416504, -8.775146, -95.20752, -9.295669, -95.625, -10.074992, -96.152344"
    },
    {
      "from": 103,
      "to": 68,
      "distance": 440221.5,
      "road_type": "land",
      "road_name": "",
      "coords": "-10.074992, -96.152344, -10.852436, -96.503906, -11.36962, -96.679687, -12.036257, -96.943359, -12.594103, -97.009277, -13.839985, -97.338867"
    },
    {
      "from": 101,
      "to": 104,
      "distance": 613975.2,
      "road_type": "land",
      "road_name": "",
      "coords": "-8.405997, -91.40625, -8.88365, -90.593262, -9.252321, -89.978027, -9.772138, -89.274902, -10.16147, -88.439941, -10.67984, -87.60498, -11.352638, -86.682129"
    },
    {
      "from": 104,
      "to": 96,
      "distance": 304267.0,
      "road_type": "land",
      "road_name": "",
      "coords": "-11.352638, -86.682129, -11.919622, -86.802979, -12.273932, -86.813965, -12.713472, -86.748047, -13.01321, -86.682129, -13.355325, -86.473389, -13.965648, -86.231689"
    },
    {
      "from": 101,
      "to": 105,
      "distance": 138548.1,
      "road_type": "land",
      "road_name": "",
      "coords": "-8.405997, -91.40625, -8.932004, -92.548828"
    },
    {
      "from": 61,
      "to": 106,
      "distance": 448448.3,
      "road_type": "land",
      "road_name": "",
      "coords": "-15.115754, -103.888758, -14.301011, -103.688965, -13.490922, -103.557129, -12.828011, -103.095703, -12.42084, -102.722168, -11.676307, -101.99707"
    },
    {
      "from": 67,
      "to": 107,
      "distance": 225937.8,
      "road_type": "land",
      "road_name": "",
      "coords": "-14.997793, -100.431519, -14.506241, -100.480957, -13.611515, -100.305176, -12.991733, -100.206299"
    },
    {
      "from": 68,
      "to": 107,
      "distance": 325102.6,
      "road_type": "land",
      "road_name": "",
      "coords": "-13.839985, -97.338867, -13.751322, -97.514648, -13.639304, -97.844238, -13.495204, -98.338623, -13.302934, -98.85498, -13.190706, -99.28894, -13.09447, -99.761353, -12.991733, -100.206299"
    },
    {
      "from": 106,
      "to": 107,
      "distance": 243397.7,
      "road_type": "land",
      "road_name": "",
      "coords": "-11.676307, -101.99707, -12.151552, -101.337891, -12.666302, -100.634766, -12.991733, -100.206299"
    },
    {
      "from": 106,
      "to": 103,
      "distance": 667479.8,
      "road_type": "land",
      "road_name": "",
      "coords": "-11.676307, -101.99707, -11.325522, -101.206055, -10.980781, -100.283203, -10.678803, -99.338379, -10.46292, -98.173828, -10.073953, -96.745605, -10.074992, -96.152344"
    },
    {
      "from": 108,
      "to": 102,
      "distance": 410418.2,
      "road_type": "land",
      "road_name": "",
      "coords": "-6.778101, -96.789551, -6.861538, -96.295166, -7.057731, -95.592041, -7.319192, -94.899902, -7.667568, -94.163818, -8.058242, -93.317871"
    },
    {
      "from": 106,
      "to": 108,
      "distance": 831148.7,
      "road_type": "land",
      "road_name": "",
      "coords": "-11.676307, -101.99707, -10.786528, -101.513672, -9.749294, -100.964355, -8.839049, -100.129395, -7.817778, -99.18457, -7.164574, -98.4375, -6.881222, -97.734375, -6.778101, -96.789551"
    },
    {
      "from": 67,
      "to": 99,
      "distance": 627895.8,
      "road_type": "sea",
      "road_name": "",
      "coords": "-14.997793, -100.431519, -16.096073, -100.140381, -17.043269, -99.920654, -18.163147, -99.30542, -18.819202, -98.272705, -18.621686, -97.130127"
    },
    {
      "from": 21,
      "to": 109,
      "distance": 1198601.1,
      "road_type": "sea",
      "road_name": "",
      "coords": "-56.446266, 52.272949, -58.264508, 50.229492, -60.108879, 46.010742, -61.333106, 44.472656, -62.873982, 40.12207, -64.318981, 37.617188"
    },
    {
      "from": 109,
      "to": 110,
      "distance": 1027654.6,
      "road_type": "sea",
      "road_name": "",
      "coords": "-64.318981, 37.617188, -66.457837, 32.475586, -68.588827, 26.191406, -69.698819, 22.324219, -70.505928, 19.555664"
    },
    {
      "from": 110,
      "to": 111,
      "distance": 789805.6,
      "road_type": "sea",
      "road_name": "",
      "coords": "-70.505928, 19.555664, -71.026776, 15.336914, -71.197395, 8.657227, -71.15488, 4.086914, -70.33069, -1.362305"
    },
    {
      "from": 111,
      "to": 112,
      "distance": 387462.6,
      "road_type": "sea",
      "road_name": "",
      "coords": "-70.33069, -1.362305, -69.346892, -5.756836, -68.686353, -6.723633, -68.169614, -6.899414, -67.807465, -7.426758"
    },
    {
      "from": 113,
      "to": 112,
      "distance": 68924.8,
      "road_type": "sea",
      "road_name": "",
      "coords": "-67.26396, -8.206787, -67.807465, -7.426758"
    },
    {
      "from": 93,
      "to": 114,
      "distance": 175681.0,
      "road_type": "land",
      "road_name": "",
      "coords": "-14.694457, -83.298674, -14.47187, -83.237915, -14.221876, -83.161011, -13.960948, -83.259888, -13.731728, -83.336792, -13.550324, -83.490601, -13.371776, -83.781738"
    },
    {
      "from": 114,
      "to": 96,
      "distance": 216601.2,
      "road_type": "land",
      "road_name": "",
      "coords": "-13.371776, -83.781738, -13.41151, -84.193726, -13.528973, -84.896851, -13.587683, -85.275879, -13.767961, -85.731812"
    },
    {
      "from": 108,
      "to": 115,
      "distance": 355946.1,
      "road_type": "land",
      "road_name": "",
      "coords": "-6.778101, -96.789551, -6.421837, -97.229004, -6.138057, -97.591553, -5.865049, -97.943115, -5.613763, -98.55835, -5.253034, -99.019775, -4.847052, -99.294434"
    },
    {
      "from": 114,
      "to": 116,
      "distance": 220753.8,
      "road_type": "land",
      "road_name": "",
      "coords": "-13.371776, -83.781738, -12.998526, -84.385986, -12.741615, -84.935303, -12.342343, -85.517578"
    },
    {
      "from": 116,
      "to": 104,
      "distance": 170725.0,
      "road_type": "land",
      "road_name": "",
      "coords": "-12.342343, -85.517578, -12.001558, -85.924072, -11.636135, -86.176758, -11.352638, -86.682129"
    },
    {
      "from": 104,
      "to": 117,
      "distance": 354321.5,
      "road_type": "land",
      "road_name": "",
      "coords": "-11.352638, -86.682129, -10.842267, -86.363525, -10.32417, -86.044922, -9.88095, -85.748291, -9.545433, -85.583496, -9.177068, -85.78125, -8.949356, -85.561523, -8.6024, -85.583496"
    },
    {
      "from": 114,
      "to": 118,
      "distance": 284560.8,
      "road_type": "land",
      "road_name": "",
      "coords": "-13.371776, -83.781738, -13.108574, -83.29834, -12.733988, -82.738037, -12.444642, -82.111816, -11.998713, -81.584473"
    },
    {
      "from": 118,
      "to": 94,
      "distance": 414125.0,
      "road_type": "land",
      "road_name": "",
      "coords": "-11.998713, -81.584473, -11.682248, -80.947266, -11.380999, -80.167236, -11.025548, -78.651123, -10.877768, -77.980957"
    },
    {
      "from": 116,
      "to": 119,
      "distance": 186674.7,
      "road_type": "land",
      "road_name": "",
      "coords": "-12.342343, -85.517578, -12.423196, -84.517822, -12.471062, -83.803711"
    },
    {
      "from": 119,
      "to": 118,
      "distance": 249588.8,
      "road_type": "land",
      "road_name": "",
      "coords": "-12.471062, -83.803711, -12.337395, -83.309326, -12.058347, -82.617188, -11.998713, -81.584473"
    },
    {
      "from": 120,
      "to": 121,
      "distance": 666357.8,
      "road_type": "land",
      "road_name": "",
      "coords": "-48.567483, -14.432187, -48.657988, -16.171875, -48.628967, -18.237305, -48.396196, -20.566406, -48.162355, -21.972656, -47.60238, -23.115234"
    },
    {
      "from": 121,
      "to": 122,
      "distance": 934819.6,
      "road_type": "land",
      "road_name": "",
      "coords": "-47.60238, -23.115234, -47.392914, -24.697266, -47.273845, -26.71875, -47.094737, -29.882813, -47.004956, -32.211914, -46.856545, -35.419922"
    },
    {
      "from": 122,
      "to": 123,
      "distance": 891656.1,
      "road_type": "land",
      "road_name": "",
      "coords": "-46.856545, -35.419922, -46.974996, -37.22168, -47.154507, -39.111328, -47.571015, -40.913086, -47.689414, -43.110352, -47.866509, -44.692383, -47.98268, -47.118976"
    },
    {
      "from": 120,
      "to": 124,
      "distance": 683118.8,
      "road_type": "land",
      "road_name": "",
      "coords": "-48.567483, -14.432187, -49.772468, -14.0625, -51.961824, -13.974609, -52.899091, -13.930664, -54.600732, -14.852336"
    },
    {
      "from": 124,
      "to": 125,
      "distance": 545676.6,
      "road_type": "land",
      "road_name": "",
      "coords": "-54.600732, -14.852336, -55.368601, -13.798828, -56.500222, -12.392578, -57.457569, -10.986328, -58.596612, -9.707043"
    },
    {
      "from": 125,
      "to": 126,
      "distance": 693085.2,
      "road_type": "land",
      "road_name": "",
      "coords": "-58.596612, -9.707043, -58.436499, -8.261719, -58.367459, -6.591797, -58.48245, -4.921875, -59.0292, -3.999023, -59.899456, -3.999023, -60.596901, -4.21875, -61.808829, -5.67016"
    },
    {
      "from": 126,
      "to": 127,
      "distance": 552078.3,
      "road_type": "land",
      "road_name": "",
      "coords": "-61.808829, -5.67016, -62.762881, -5.537109, -63.712121, -5.668945, -64.403794, -5.493164, -65.004331, -5.625, -65.736461, -6.37207, -66.112721, -6.899414, -66.281835, -7.371826, -66.49295, -7.811279"
    },
    {
      "from": 127,
      "to": 113,
      "distance": 95636.4,
      "road_type": "land",
      "road_name": "",
      "coords": "-66.49295, -7.811279, -66.67622, -8.162842, -66.814949, -8.327637, -66.995847, -8.470459, -67.26396, -8.206787"
    },
    {
      "from": 114,
      "to": 119,
      "distance": 101297.2,
      "road_type": "land",
      "road_name": "",
      "coords": "-13.371776, -83.781738, -13.153379, -83.748779, -12.934086, -83.754272, -12.757442, -83.737793, -12.471062, -83.803711"
    },
    {
      "from": 116,
      "to": 96,
      "distance": 172797.3,
      "road_type": "land",
      "road_name": "",
      "coords": "-12.342343, -85.517578, -12.564599, -85.605469, -12.800276, -85.649414, -12.97154, -85.627441, -13.131993, -85.517578, -13.292341, -85.495605, -13.495297, -85.495605, -13.779396, -85.698853"
    },
    {
      "from": 127,
      "to": 128,
      "distance": 30266.9,
      "road_type": "land",
      "road_name": "",
      "coords": "-66.49295, -7.811279, -66.477669, -7.130127"
    },
    {
      "from": 128,
      "to": 129,
      "distance": 859304.3,
      "road_type": "land",
      "road_name": "",
      "coords": "-66.477669, -7.130127, -66.482051, -6.394043, -66.468902, -5.163574, -66.573422, -3.010254, -66.608322, -1.647949, -66.686668, 0.812988, -66.599602, 3.010254, -66.538473, 4.724121, -66.424549, 6.899414, -66.265946, 8.283691, -66.070732, 9.755859, -65.847065, 10.744629, -65.65037, 11.752391"
    },
    {
      "from": 129,
      "to": 130,
      "distance": 31376.3,
      "road_type": "sea",
      "road_name": "",
      "coords": "-65.65037, 11.752391, -65.589797, 12.420044"
    },
    {
      "from": 130,
      "to": 110,
      "distance": 660038.7,
      "road_type": "sea",
      "road_name": "",
      "coords": "-65.589797, 12.420044, -65.816111, 12.623291, -66.142402, 13.227539, -66.425052, 14.106445, -66.613181, 14.644775, -66.786912, 15.018311, -67.211666, 15.490723, -67.469709, 15.644531, -67.828805, 16.138916, -68.051499, 16.45752, -68.235453, 16.831055, -68.434088, 17.380371, -68.68295, 18.149414, -69.035404, 18.687744, -69.378423, 19.138184, -69.601562, 19.577637, -69.8186, 20.083008, -69.98085, 20.039063, -70.312734, 19.764404, -70.505928, 19.555664"
    },
    {
      "from": 130,
      "to": 109,
      "distance": 1219692.7,
      "road_type": "sea",
      "road_name": "",
      "coords": "-65.589797, 12.420044, -65.61151, 13.908691, -65.747177, 15.79834, -65.989592, 17.468262, -66.353349, 19.138184, -66.528901, 20.544434, -66.406144, 24.455566, -66.043152, 28.103027, -65.864181, 31.618652, -65.438642, 33.530273, -64.318981, 37.617188"
    },
    {
      "from": 6,
      "to": 131,
      "distance": 1051118.6,
      "road_type": "land",
      "road_name": "",
      "coords": "-10.748318, -72.224121, -10.08807, -70.927734, -9.655353, -70.839844, -9.048619, -71.235352, -8.397412, -71.279297, -7.875654, -71.05957, -7.396797, -70.136719, -7.396797, -69.433594, -7.222536, -68.730469, -6.742978, -68.291016, -6.131949, -67.719727, -5.563935, -67.719727, -4.426317, -67.719727"
    },
    {
      "from": 131,
      "to": 132,
      "distance": 1313449.5,
      "road_type": "land",
      "road_name": "",
      "coords": "-4.426317, -67.719727, -3.812999, -64.291992, -3.286947, -60.732422, -1.882905, -58.710938, -0.095551, -57.282715"
    },
    {
      "from": 131,
      "to": 133,
      "distance": 2238186.3,
      "road_type": "land",
      "road_name": "",
      "coords": "-4.426317, -67.719727, -3.55001, -68.466797, -2.979952, -69.609375, -2.234054, -70.444336, -0.873002, -71.542969, 0.005407, -72.597656, 0.620304, -73.87207, 1.147305, -75.761719, 1.805914, -77.387695, 1.93761, -78.925781, 2.288747, -80.595703, 2.376519, -82.089844, 2.332634, -83.71582, 1.602787, -85.539551"
    },
    {
      "from": 132,
      "to": 134,
      "distance": 1759422.8,
      "road_type": "land",
      "road_name": "",
      "coords": "-0.095551, -57.282715, -2.446364, -51.152344, -4.210743, -46.845703, -4.320244, -45.087891, -4.123131, -42.231445"
    },
    {
      "from": 134,
      "to": 135,
      "distance": 2845091.3,
      "road_type": "land",
      "road_name": "",
      "coords": "-4.123131, -42.231445, -4.644568, -36.254883, -4.907186, -33.354492, -5.606979, -28.87207, -6.13128, -26.411133, -7.26544, -22.763672, -7.221869, -19.907227, -6.349589, -16.962891"
    },
    {
      "from": 135,
      "to": 136,
      "distance": 1427374.8,
      "road_type": "land",
      "road_name": "",
      "coords": "-6.349589, -16.962891, -5.213442, -11.293945, -3.987609, -8.920898, -2.935416, -6.547852, -2.189493, -4.87793"
    },
    {
      "from": 136,
      "to": 137,
      "distance": 298144.5,
      "road_type": "land",
      "road_name": "",
      "coords": "-2.189493, -4.87793, 0.365615, -4.064941"
    },
    {
      "from": 131,
      "to": 138,
      "distance": 1048461.5,
      "road_type": "land",
      "road_name": "",
      "coords": "-4.426317, -67.719727, -5.701439, -66.269531, -7.207103, -64.6875, -7.925503, -63.654785, -8.186435, -61.831055, -7.838489, -60.710449, -7.415532, -59.699647"
    },
    {
      "from": 138,
      "to": 132,
      "distance": 1027641.2,
      "road_type": "land",
      "road_name": "",
      "coords": "-7.415532, -59.699647, -6.901976, -58.227539, -6.116481, -57.348633, -5.657733, -56.821289, -4.804827, -56.469727, -3.687906, -56.293945, -2.591518, -56.381836, -1.581993, -56.601563, -0.923322, -56.865234, -0.095551, -57.282715"
    },
    {
      "from": 138,
      "to": 134,
      "distance": 2020141.4,
      "road_type": "land",
      "road_name": "",
      "coords": "-7.415532, -59.699647, -7.795193, -57.875977, -7.708152, -55.83252, -7.816951, -53.283691, -7.795193, -50.866699, -6.880393, -48.295898, -5.461232, -44.450684, -4.123131, -42.231445"
    },
    {
      "from": 121,
      "to": 139,
      "distance": 492402.8,
      "road_type": "land",
      "road_name": "",
      "coords": "-47.60238, -23.115234, -49.265336, -22.5, -50.398513, -21.708984, -51.719417, -20.670795"
    },
    {
      "from": 139,
      "to": 124,
      "distance": 504527.0,
      "road_type": "land",
      "road_name": "",
      "coords": "-51.719417, -20.670795, -52.582525, -19.160156, -53.480548, -17.578125, -54.206112, -16.12793, -54.600732, -14.852336"
    },
    {
      "from": 120,
      "to": 139,
      "distance": 581437.6,
      "road_type": "land",
      "road_name": "",
      "coords": "-48.567483, -14.432187, -49.490691, -15.600586, -50.534962, -17.050781, -51.255235, -18.193359, -51.719417, -20.670795"
    },
    {
      "from": 120,
      "to": 140,
      "distance": 1498534.5,
      "road_type": "land",
      "road_name": "",
      "coords": "-48.567483, -14.432187, -48.236473, -14.018555, -47.987204, -13.974609, -47.781015, -13.776855, -47.618434, -13.359375, -47.529539, -12.919922, -47.529539, -12.392578, -47.633235, -11.711426, -47.648032, -11.118164, -47.662824, -10.59082, -47.633235, -9.667969, -47.440494, -9.448242, -47.052885, -9.492188, -46.873032, -9.755859, -46.647365, -10.107422, -46.466151, -10.634766, -46.329843, -10.854492, -46.025718, -11.271973, -45.71991, -11.425781, -45.474051, -11.315918, -45.335283, -10.854492, -45.288951, -10.371094, -45.180696, -9.84375, -45.180696, -9.448242, -45.072234, -8.898926, -45.072234, -8.459473, -44.979103, -8.02002, -45.535617, -6.416016, -45.811829, -5.097656, -45.781206, -2.834473, -45.650189, -1.867676"
    },
    {
      "from": 140,
      "to": 141,
      "distance": 2717958.1,
      "road_type": "land",
      "road_name": "",
      "coords": "-45.650189, -1.867676, -45.635342, 0.395508, -45.450771, 2.021484, -45.141806, 5.317383, -44.8, 7.250977, -44.204811, 10.283203, -43.348567, 12.744141, -42.350364, 14.414063, -41.005431, 16.523438, -39.293385, 19.423828, -37.647541, 23.005371, -37.351351, 24.279785, -37.106548, 25.257568, -36.904867, 26.125488, -36.887304, 27.004395, -37.00139, 27.575684, -37.014475, 27.92005"
    },
    {
      "from": 141,
      "to": 142,
      "distance": 62676.3,
      "road_type": "sea",
      "road_name": "",
      "coords": "-37.014475, 27.92005, -37.41216, 28.421631"
    },
    {
      "from": 142,
      "to": 24,
      "distance": 1878457.3,
      "road_type": "sea",
      "road_name": "",
      "coords": "-37.41216, 28.421631, -38.410176, 30.102539, -39.807431, 33.618164, -40.679089, 35.683594, -42.776686, 41.308594, -43.912261, 44.758301, -43.928079, 46.230469, -44.572786, 48.669434"
    },
    {
      "from": 143,
      "to": 144,
      "distance": 75315.0,
      "road_type": "sea",
      "road_name": "",
      "coords": "-60.098829, 8.608343, -60.616221, 9.492188"
    },
    {
      "from": 144,
      "to": 130,
      "distance": 581698.0,
      "road_type": "sea",
      "road_name": "",
      "coords": "-60.616221, 9.492188, -61.319595, 9.689941, -61.893937, 9.624023, -62.528698, 9.997559, -63.150216, 10.063477, -63.63218, 10.50293, -64.335325, 10.942383, -64.731917, 11.293945, -65.067288, 11.931152, -65.589797, 12.420044"
    },
    {
      "from": 144,
      "to": 142,
      "distance": 2989853.0,
      "road_type": "sea",
      "road_name": "",
      "coords": "-60.616221, 9.492188, -60.430218, 10.942383, -60.037724, 12.963867, -59.640509, 14.589844, -59.058346, 16.303711, -57.128381, 18.808594, -55.271872, 20.390625, -53.429139, 21.972656, -51.283659, 23.554688, -47.394265, 25.048828, -44.837395, 26.191406, -41.83541, 27.070313, -39.639252, 27.949219, -37.41216, 28.421631"
    },
    {
      "from": 145,
      "to": 128,
      "distance": 515079.8,
      "road_type": "land",
      "road_name": "",
      "coords": "-69.403623, 2.086943, -69.276803, 1.40625, -69.187253, 0.681152, -69.077735, -0.186768, -68.991299, -0.812988, -68.837234, -1.669922, -68.698053, -2.373047, -68.525865, -3.043213, -68.275257, -3.735352, -68.058824, -4.350586, -67.397143, -5.548096, -67.116973, -5.943604, -66.880992, -6.394043, -66.68186, -6.800537, -66.477669, -7.130127"
    },
    {
      "from": 145,
      "to": 111,
      "distance": 167509.2,
      "road_type": "sea",
      "road_name": "",
      "coords": "-69.403623, 2.086943, -69.679884, 1.098633, -69.982752, -0.087891, -70.33069, -1.362305"
    },
    {
      "from": 145,
      "to": 129,
      "distance": 611694.6,
      "road_type": "land",
      "road_name": "",
      "coords": "-69.403623, 2.086943, -69.123632, 4.130859, -68.55285, 6.459961, -67.901217, 8.613281, -67.31565, 10.107422, -66.888419, 10.942383, -66.365704, 11.733398, -65.65037, 11.752391"
    },
    {
      "from": 138,
      "to": 146,
      "distance": 2002554.2,
      "road_type": "land",
      "road_name": "",
      "coords": "-7.415532, -59.699647, -9.882413, -58.31543, -12.596164, -56.865234, -14.262224, -55.50293, -15.873818, -53.657227, -17.095177, -51.943359, -18.475295, -49.96582, -19.927002, -48.955078, -21.287076, -48.349124"
    },
    {
      "from": 146,
      "to": 135,
      "distance": 3790227.3,
      "road_type": "land",
      "road_name": "",
      "coords": "-21.287076, -48.349124, -20.295495, -42.626953, -18.555864, -37.96875, -13.491915, -26.982422, -10.657506, -22.060547, -6.349589, -16.962891"
    },
    {
      "from": 146,
      "to": 147,
      "distance": 3321676.9,
      "road_type": "land",
      "road_name": "",
      "coords": "-21.287076, -48.349124, -22.183537, -45.571289, -23.236954, -43.417969, -24.28212, -41.52832, -25.358451, -38.759766, -26.425285, -36.694336, -26.346592, -33.574219, -25.952328, -29.707031, -24.761643, -23.027344, -24.362167, -20.742188, -24.202022, -18.984375, -24.203911, -16.980351"
    },
    {
      "from": 147,
      "to": 136,
      "distance": 2788136.2,
      "road_type": "land",
      "road_name": "",
      "coords": "-24.203911, -16.980351, -23.784474, -16.809082, -23.512898, -16.715698, -23.129729, -16.430054, -22.68469, -16.149902, -22.385498, -15.952148, -22.01442, -15.792847, -21.749495, -15.617065, -20.880861, -14.897461, -20.078521, -14.501953, -19.292782, -13.820801, -18.378253, -13.249512, -17.165322, -12.370605, -13.634985, -10.327148, -11.362445, -8.920898, -9.115019, -7.558594, -6.722519, -6.635742, -3.880091, -5.229492, -2.189493, -4.87793"
    },
    {
      "from": 147,
      "to": 147,
      "distance": 52180.0,
      "road_type": "sea",
      "road_name": "",
      "coords": "-24.203911, -16.980351, -24.531348, -16.611328"
    },
    {
      "from": 140,
      "to": 148,
      "distance": 87049.9,
      "road_type": "sea",
      "road_name": "",
      "coords": "-45.650189, -1.867676, -44.978266, -2.438965"
    },
    {
      "from": 148,
      "to": 147,
      "distance": 2685688.8,
      "road_type": "sea",
      "road_name": "",
      "coords": "-44.978266, -2.438965, -44.471166, -3.284912, -44.101724, -3.570557, -43.642615, -3.625488, -43.31594, -3.636475, -42.905874, -3.625488, -42.226567, -3.911133, -41.589165, -4.306641, -41.077978, -4.855957, -40.312061, -6.328125, -39.774065, -7.800293, -38.169205, -9.360352, -36.704534, -10.986328, -35.569472, -11.777344, -33.690311, -12.612305, -31.507388, -13.710938, -29.501895, -14.677734, -27.883774, -15.336914, -25.554295, -16.138916, -24.531348, -16.611328"
    },
    {
      "from": 97,
      "to": 95,
      "distance": 983917.4,
      "road_type": "sea",
      "road_name": "",
      "coords": "-13.314275, -74.707031, -13.645293, -75.047607, -13.773306, -75.476074, -13.847947, -75.992432, -14.018466, -77.662354, -14.167567, -78.409424, -14.263365, -79.16748, -14.359123, -79.881592, -14.699263, -80.980225, -15.049477, -81.68335, -15.303818, -82.386475, -15.473208, -82.935791, -15.44195, -83.419189"
    }
  ]
}